Model/SRGan.py
Model/__init__.py
SRGAN/__init__.py
SRGAN/networks.py
SRGAN/training_ckp_generator/__init__.py
gan_recover_image/SRGan.py
gan_recover_image/__init__.py
result/__init__.py
gan_recover-0.0.11.dist-info/LICENSE
gan_recover-0.0.11.dist-info/METADATA
gan_recover-0.0.11.dist-info/WHEEL
gan_recover-0.0.11.dist-info/top_level.txt
gan_recover-0.0.11.dist-info/RECORD
