Metadata-Version: 2.1
Name: gan-recover
Version: 0.0.11
Summary: A small package
Home-page: https://github.com/pypa/sampleproject
Author: Tu Meo
Author-email: tumeotl@gmail.com
License: UNKNOWN
Platform: UNKNOWN
Classifier: Programming Language :: Python :: 3
Classifier: License :: OSI Approved :: MIT License
Classifier: Operating System :: OS Independent
Requires-Python: >=3.6
Requires-Dist: PyYAML
Requires-Dist: pandas (==0.23.3)
Requires-Dist: numpy (>=1.14.5)
Requires-Dist: matplotlib (>=2.2.0)
Requires-Dist: jupyter
